mlcli22.py
mlcli22-1.0.1.dist-info/licenses/LICENSE           
mlcli22-1.0.1.dist-info/METADATA
mlcli22-1.0.1.dist-info/WHEEL
mlcli22-1.0.1.dist-info/entry_points.txt
mlcli22-1.0.1.dist-info/top_level.txt
mlcli22-1.0.1.dist-info/RECORD
