Metadata-Version: 2.4
Name: mlcli22
Version: 1.0.1
Summary: CLI para gestionar proyectos de Machine Learning
Home-page: https://github.com/ysisco/mlcli22
Author: Yilber Sisco
Classifier: Programming Language :: Python :: 3
Classifier: License :: OSI Approved :: MIT License
Classifier: Operating System :: OS Independent
Requires-Python: >=3.8
License-File: LICENSE           
Requires-Dist: typer
Requires-Dist: PyYAML
Dynamic: author
Dynamic: classifier
Dynamic: description-content-type
Dynamic: home-page
Dynamic: license-file
Dynamic: requires-dist
Dynamic: requires-python
Dynamic: summary
